djangomultitenant
