Metadata-Version: 1.1
Name: djangomultitenant
Version: 0.0.2
Summary: A django app which helps to implement multitenancy easily
Home-page: https://github.com/akhilputhiry/djangomultitenant
Author: Akhil Lawrence
Author-email: akhilputhiry@gmail.com
License: GNU GPLv3
Keywords: multitenant,multitenancy,django multitenant,django multitenancy
Platform: UNKNOWN
Classifier: Development Status :: 4 - Beta
Classifier: Topic :: Internet :: WWW/HTTP
Classifier: Framework :: Django :: 1.10
Classifier: Framework :: Django :: 1.11
Classifier: Programming Language :: Python :: 2.7
Classifier: Programming Language :: Python :: 3.6
Classifier: License :: Freeware
